types.py
generation_types-0.1.0.dist-info/METADATA
generation_types-0.1.0.dist-info/WHEEL
generation_types-0.1.0.dist-info/RECORD
