Metadata-Version: 2.1
Name: generation-types
Version: 0.1.0
Summary: generation API data model
Author: battery_al
Author-email: allenlawrence94@gmail.com
Requires-Python: >=3.8,<4.0
Classifier: Programming Language :: Python :: 3
Classifier: Programming Language :: Python :: 3.8
Classifier: Programming Language :: Python :: 3.9
Classifier: Programming Language :: Python :: 3.10
Classifier: Programming Language :: Python :: 3.11
Requires-Dist: pydantic (>=1.5.1,<2.0.0)
